hdo_nbdev_template/__init__.py
hdo_nbdev_template/_modidx.py
hdo_nbdev_template/core.py
hdo_nbdev_template/utils.py
hdo_nbdev_template-0.0.1.dist-info/METADATA
hdo_nbdev_template-0.0.1.dist-info/WHEEL
hdo_nbdev_template-0.0.1.dist-info/entry_points.txt
hdo_nbdev_template-0.0.1.dist-info/top_level.txt
hdo_nbdev_template-0.0.1.dist-info/RECORD
