Metadata-Version: 2.1
Name: hdo_nbdev_template
Version: 0.0.1
Summary: project page
Home-page: https://github.com/hdocmsu/hdo_nbdev_template/
Author: Hung P. Do, PhD, MSEE
Author-email: clinicalcollaborations@gmail.com
License: None
Keywords: nbdev,mri,medical imaging,deep learning,magnetic resonance imaging
Classifier: Development Status :: 3 - Alpha
Classifier: Intended Audience :: Developers
Classifier: Natural Language :: English
Classifier: Programming Language :: Python :: 3.7
Classifier: Programming Language :: Python :: 3.8
Classifier: Programming Language :: Python :: 3.9
Classifier: Programming Language :: Python :: 3.10
Classifier: Programming Language :: Python :: 3.11
Classifier: Programming Language :: Python :: 3.12
Requires-Python: >=3.7
Requires-Dist: numpy
Requires-Dist: matplotlib
Requires-Dist: pandas
Provides-Extra: dev
